odoo/addons/shopfloor_mobile/README.rst
odoo/addons/shopfloor_mobile/__init__.py
odoo/addons/shopfloor_mobile/__manifest__.py
odoo/addons/shopfloor_mobile/i18n/es_AR.po
odoo/addons/shopfloor_mobile/i18n/shopfloor_mobile.pot
odoo/addons/shopfloor_mobile/readme/CONTRIBUTORS.rst
odoo/addons/shopfloor_mobile/readme/CREDITS.rst
odoo/addons/shopfloor_mobile/readme/DESCRIPTION.rst
odoo/addons/shopfloor_mobile/readme/HISTORY.rst
odoo/addons/shopfloor_mobile/readme/ROADMAP.rst
odoo/addons/shopfloor_mobile/readme/USAGE.rst
odoo/addons/shopfloor_mobile/static/description/icon.png
odoo/addons/shopfloor_mobile/static/description/index.html
odoo/addons/shopfloor_mobile/static/wms/.gitignore
odoo/addons/shopfloor_mobile/static/wms/src/screen.js
odoo/addons/shopfloor_mobile/static/wms/src/wms_utils.js
odoo/addons/shopfloor_mobile/static/wms/src/components/batch_picking_detail.js
odoo/addons/shopfloor_mobile/static/wms/src/components/batch_picking_line_detail.js
odoo/addons/shopfloor_mobile/static/wms/src/components/misc.js
odoo/addons/shopfloor_mobile/static/wms/src/components/packaging-qty-picker.js
odoo/addons/shopfloor_mobile/static/wms/src/components/detail/detail_location.js
odoo/addons/shopfloor_mobile/static/wms/src/components/detail/detail_lot.js
odoo/addons/shopfloor_mobile/static/wms/src/components/detail/detail_operation.js
odoo/addons/shopfloor_mobile/static/wms/src/components/detail/detail_package.js
odoo/addons/shopfloor_mobile/static/wms/src/components/detail/detail_picking.js
odoo/addons/shopfloor_mobile/static/wms/src/components/detail/detail_product.js
odoo/addons/shopfloor_mobile/static/wms/src/components/detail/detail_transfer.js
odoo/addons/shopfloor_mobile/static/wms/src/components/forms/form_edit_stock_picking.js
odoo/addons/shopfloor_mobile/static/wms/src/components/scenario_picking_detail/mixins.js
odoo/addons/shopfloor_mobile/static/wms/src/components/scenario_picking_detail/picking_select.js
odoo13_addon_shopfloor_mobile-13.0.2.5.1.dist-info/METADATA
odoo13_addon_shopfloor_mobile-13.0.2.5.1.dist-info/WHEEL
odoo13_addon_shopfloor_mobile-13.0.2.5.1.dist-info/top_level.txt
odoo13_addon_shopfloor_mobile-13.0.2.5.1.dist-info/RECORD
