Metadata-Version: 2.1
Name: odoo13-addon-shopfloor-mobile
Version: 13.0.2.5.1
Summary: Mobile frontend for WMS Shopfloor app
Home-page: https://github.com/OCA/wms
Author: Camptocamp, BCIM, Akretion, Odoo Community Association (OCA)
Author-email: support@odoo-community.org
License: AGPL-3
Platform: UNKNOWN
Classifier: Programming Language :: Python
Classifier: Framework :: Odoo
Classifier: Framework :: Odoo :: 13.0
Classifier: License :: OSI Approved :: GNU Affero General Public License v3
Classifier: Development Status :: 3 - Alpha
Requires-Python: >=3.5
Requires-Dist: odoo13-addon-shopfloor
Requires-Dist: odoo13-addon-shopfloor-mobile-base
Requires-Dist: odoo (<13.1dev,>=13.0a)
